{"available": true, "player": {"id": 8481068, "name": "Yegor Sharangovich"}, "bio": {"position": "C", "shoots": "L", "age": 28.1, "heightIn": 74, "weightLb": 196, "draft": {"year": 2018, "round": 5, "overall": 141}}, "goalie": null, "usage": {"season": 20252026, "seasonLabel": "2025-26", "team": "CGY", "gamesPlayed": 78, "toiMinutes": 1251, "ppToi": 115, "pkToi": 72, "partners": [{"name": "Joel Farabee", "toiMin": 360, "chemNet60": 0.164}, {"name": "Kevin Bahl", "toiMin": 331, "chemNet60": -0.417}]}, "boxscore": {"latest": {"gp": 78, "g": 15, "a": 14, "p": 29, "shots": 142, "toiMinutes": 1251, "plusMinus": -20, "pim": 12, "shPct": 10.6, "season": 20252026, "seasonLabel": "2025-26"}, "career": {"gp": 438, "g": 116, "a": 110, "p": 226, "shots": 862, "toiMinutes": 7131, "plusMinus": -79, "pim": 71, "shPct": 13.5, "seasons": 6}}, "jockTax": {"available": true, "team": "CGY", "birthCountry": "BLR", "years": 5, "grossTotal": 28750000, "netTotal": 15723324, "effRate": 0.453, "treatyBonus": true, "sbShare": 0.17, "aav": 5750000, "hereNet": 3144665, "best": {"team": "DAL", "net": 3510415, "noTax": true}, "worst": {"team": "SJS", "net": 2935190}}, "dealGrade": {"grade": "C", "verdict": "slight overpay", "aav": 5750000.0, "fairAav": 3997219.0, "surplusPerYr": -2798236.0, "anchor": "WAR (term-matched)", "finishing": "neutral", "notes": ["graded as the bet at signing (2024, age 27); the deal's 6.5% cap share is ~$6.8M in today's cap"], "aavToday": 6795455.0, "dealCapPct": 6.5, "fairCapPct": 3.2, "signingYear": 2024, "endAge": 32, "afterTax": {"netPerYr": 3246519.0, "effRate": 0.435}}, "playoffStats": {"gp": 3, "g": 0, "a": 0, "p": 0, "toiPerGp": 11.0, "runs": [{"season": 20222023, "gp": 3, "g": 0, "a": 0}]}, "shotProfile": {"totalShots": 1303, "types": [{"type": "wrist", "shots": 642, "pct": 49, "goals": 49, "shPct": 7.6, "xg": 49.8}, {"type": "snap", "shots": 275, "pct": 21, "goals": 34, "shPct": 12.4, "xg": 27.8}, {"type": "slap", "shots": 136, "pct": 10, "goals": 8, "shPct": 5.9, "xg": 10.4}, {"type": "tip-in", "shots": 121, "pct": 9, "goals": 19, "shPct": 15.7, "xg": 9.3}, {"type": "backhand", "shots": 93, "pct": 7, "goals": 12, "shPct": 12.9, "xg": 7.8}, {"type": "deflected", "shots": 26, "pct": 2, "goals": 1, "shPct": 3.8, "xg": 2.4}, {"type": "wrap-around", "shots": 5, "pct": 0, "goals": 0, "shPct": 0.0, "xg": 0.1}], "power": {"season_id": 20252026, "top_shot_mph": 96.14, "top_shot_pct": 98.0, "avg_shot_mph": 56.605, "shots_over_100": 0, "shots_over_100_pct": 0.0, "hardest_matchup": "WSH@CGY", "hardest_date": "2026-01-23"}}, "monthlySplits": {"available": true, "season": 20252026, "months": [{"month": "2025-10", "gp": 10, "toiPerGp": 14.9, "p60": 1.21, "g": 2, "a": 1, "p": 3, "ixg": 2.6, "gax": -0.6, "onXgf": 4.4, "onXga": 4.6, "onXgPct": 49, "qoc": 17.6, "qot": 17.7}, {"month": "2025-11", "gp": 13, "toiPerGp": 14.3, "p60": 1.29, "g": 1, "a": 3, "p": 4, "ixg": 2.1, "gax": -1.1, "onXgf": 6.9, "onXga": 7.1, "onXgPct": 49, "qoc": 17.6, "qot": 18.2}, {"month": "2025-12", "gp": 13, "toiPerGp": 17.5, "p60": 1.58, "g": 5, "a": 1, "p": 6, "ixg": 3.8, "gax": 1.2, "onXgf": 7.9, "onXga": 8.7, "onXgPct": 48, "qoc": 17.6, "qot": 18.8}, {"month": "2026-01", "gp": 14, "toiPerGp": 17.2, "p60": 1.74, "g": 3, "a": 4, "p": 7, "ixg": 3.3, "gax": -0.3, "onXgf": 6.6, "onXga": 8.2, "onXgPct": 45, "qoc": 17.7, "qot": 18.6}, {"month": "2026-02", "gp": 4, "toiPerGp": 17.5, "p60": 0.0, "g": 0, "a": 0, "p": 0, "ixg": 0.9, "gax": -0.9, "onXgf": 3.2, "onXga": 2.8, "onXgPct": 54, "qoc": 18.6, "qot": 18.6}, {"month": "2026-03", "gp": 16, "toiPerGp": 16.1, "p60": 1.86, "g": 3, "a": 5, "p": 8, "ixg": 3.6, "gax": 0.4, "onXgf": 7.0, "onXga": 10.1, "onXgPct": 41, "qoc": 17.8, "qot": 16.4}, {"month": "2026-04", "gp": 8, "toiPerGp": 14.9, "p60": 0.5, "g": 1, "a": 0, "p": 1, "ixg": 0.8, "gax": 0.2, "onXgf": 2.8, "onXga": 5.8, "onXgPct": 32, "qoc": 17.9, "qot": 16.7}]}, "preNhl": {"seasons": [{"seasonYear": 2015, "league": "mhl", "teams": "Dinamo-Raubichi", "gp": 30, "g": 6, "a": 6, "p": 12, "ppg": 0.4}, {"seasonYear": 2018, "league": "ahl", "teams": "BNG", "gp": 68, "g": 9, "a": 8, "p": 17, "ppg": 0.25}, {"seasonYear": 2019, "league": "ahl", "teams": "BNG", "gp": 57, "g": 10, "a": 15, "p": 25, "ppg": 0.44}], "note": "The pre-NHL production record. Scoring is NOT comparable across leagues or to the NHL -- this is the biography, not a translation."}, "seasons": [{"season": 20202021, "totalWar": 0.61, "evWar": 0.21, "stWar": -0.03, "penaltyWar": 0.29, "faceoffWar": -0.07, "penaltyGoals": 1.75, "toiMinutes": 709.0, "offRapm": 0.011, "defRapm": -0.053, "totalRapm": -0.042, "onIceXgPct": 48.2, "offIceXgPct": 49.7, "relXgPct": -1.5, "seasonLabel": "2020-21"}, {"season": 20212022, "totalWar": 1.24, "evWar": 0.97, "stWar": -0.04, "penaltyWar": 0.08, "faceoffWar": -0.07, "penaltyGoals": 0.48, "toiMinutes": 1004.0, "offRapm": 0.018, "defRapm": 0.18, "totalRapm": 0.197, "onIceXgPct": 53.2, "offIceXgPct": 50.4, "relXgPct": 2.8, "seasonLabel": "2021-22"}, {"season": 20222023, "totalWar": 0.48, "evWar": 0.21, "stWar": -0.0, "penaltyWar": 0.09, "faceoffWar": -0.05, "penaltyGoals": 0.51, "toiMinutes": 866.0, "offRapm": -0.023, "defRapm": -0.04, "totalRapm": -0.063, "onIceXgPct": 53.9, "offIceXgPct": 56.1, "relXgPct": -2.2, "seasonLabel": "2022-23"}, {"season": 20232024, "totalWar": 1.43, "evWar": 0.98, "stWar": 0.11, "penaltyWar": 0.13, "faceoffWar": -0.13, "penaltyGoals": 0.8, "toiMinutes": 1001.0, "offRapm": 0.056, "defRapm": 0.146, "totalRapm": 0.202, "onIceXgPct": 51.6, "offIceXgPct": 49.4, "relXgPct": 2.2, "seasonLabel": "2023-24"}, {"season": 20242025, "totalWar": 0.8, "evWar": 0.6, "stWar": -0.03, "penaltyWar": 0.01, "faceoffWar": -0.04, "penaltyGoals": 0.04, "toiMinutes": 916.0, "offRapm": 0.05, "defRapm": 0.034, "totalRapm": 0.084, "onIceXgPct": 50.0, "offIceXgPct": 49.4, "relXgPct": 0.5, "seasonLabel": "2024-25"}, {"season": 20252026, "totalWar": 0.16, "evWar": -0.14, "stWar": -0.0, "penaltyWar": 0.08, "faceoffWar": -0.05, "penaltyGoals": 0.46, "toiMinutes": 952.0, "offRapm": -0.076, "defRapm": -0.127, "totalRapm": -0.203, "onIceXgPct": 45.2, "offIceXgPct": 47.8, "relXgPct": -2.6, "seasonLabel": "2025-26"}], "multiYearRapm": {"seasons": "2023-2026", "offRapm": 0.024, "defRapm": -0.009, "totalRapm": 0.016, "toiMinutes": 2868.3}, "finishing": {"shots": 1303, "goals": 124, "goalsAboveExpected": 16.0, "gaxPer100Regressed": 0.88, "reliability": 0.715}, "marketValue": {"valueWar": 0.8, "seasons": 3, "capHit": 5750000, "yearsRemaining": 4, "expiryStatus": "UFA", "productionValue": 4543676, "expiryYear": 2030, "surplus": -1206324, "verdict": "slight overpay", "projection": {"yearsRemaining": 4, "projectedWar": [0.77, 0.73, 0.69, 0.64], "projectedValuePerYear": [4402351, 4213918, 4025484, 3789941], "avgProjectedValue": 4107924, "avgProjectedSurplus": -1642076, "totalProjectedValue": 16431694, "totalCap": 23000000, "totalProjectedSurplus": -6568306, "verdict": "slight overpay"}, "projected": {"projWar": 0.64, "pp60": 1.85, "projValue": 3789941}, "flag": null}, "assetValue": {"age": 26.6, "tradeValueDollars": -6568306, "acqCostWar7": 0.93, "acqPicks": "~ #22", "marketValueWar7": 1.44, "marketValueN": 6, "marketThin": false, "marketModeled": false, "marketPremium": "motor", "controlYears": 4, "assetClass": "contract", "projectedWar": [0.77, 0.73, 0.69, 0.64], "surplus": -1206324, "projAav": null, "projTerm": null, "verdict": "slight overpay", "flag": null}, "tradeComps": {"available": true, "player": {"id": 8481068, "group": "F", "age": 28.1, "war": 0.8, "capHit": 5750000, "yearsLeft": 4}, "comps": [{"name": "David Jones", "date": "2013-06-27", "season": "2013", "warAtTrade": 0.37, "ageAtTrade": 28.9, "gaveUp": "COL", "acquiredBy": "CGY", "returnPlayers": ["Cory Sarich", "Alex Tanguay"], "returnPicks": [], "package": false, "retained": false, "capHit": 4000000, "yearsLeft": 4, "similar": 93, "returnValue": 0.83, "traded": {"name": "David Jones", "age": 28.9, "war": 0.8, "points": 9}, "tradeId": "2013-06-27-CGY-COL", "fullTrade": {"out": [{"name": "David Jones", "age": 28.9, "war": 0.8, "points": 9}], "outPicks": [], "in": [{"name": "Cory Sarich", "age": 34.9, "war": -0.0, "points": 2}, {"name": "Alex Tanguay", "age": 33.6, "war": 1.6, "points": 27}], "inPicks": [], "gaveUp": "COL", "acquiredBy": "CGY"}, "gotBack": [{"name": "Cory Sarich", "age": 34.9, "war": -0.0, "points": 2}, {"name": "Alex Tanguay", "age": 33.6, "war": 1.6, "points": 27}]}, {"name": "Carl Hagelin", "date": "2016-01-16", "season": "2016", "warAtTrade": 0.99, "ageAtTrade": 27.4, "gaveUp": "ANA", "acquiredBy": "PIT", "returnPlayers": ["David Perron", "Adam Clendening"], "returnPicks": [], "package": false, "retained": false, "capHit": 4000000, "yearsLeft": 4, "similar": 93, "returnValue": 1.95, "traded": {"name": "Carl Hagelin", "age": 27.4, "war": 0.3, "points": 36}, "tradeId": "2016-01-16-PIT-ANA", "fullTrade": {"out": [{"name": "Carl Hagelin", "age": 27.4, "war": 0.3, "points": 36}], "outPicks": [], "in": [{"name": "David Perron", "age": 27.6, "war": 3.7, "points": 42}, {"name": "Adam Clendening", "age": 23.2, "war": 0.0, "points": 3}], "inPicks": [], "gaveUp": "ANA", "acquiredBy": "PIT"}, "gotBack": [{"name": "David Perron", "age": 27.6, "war": 3.7, "points": 42}, {"name": "Adam Clendening", "age": 23.2, "war": 0.0, "points": 3}]}, {"name": "Andrew Shaw", "date": "2019-06-30", "season": "2019", "warAtTrade": 0.0, "ageAtTrade": 27.9, "gaveUp": "MTL", "acquiredBy": "CHI", "returnPlayers": [], "returnPicks": ["2nd ('20)", "3rd ('21)"], "package": true, "retained": false, "capHit": 3900000, "yearsLeft": 4, "similar": 92, "returnValue": 0.74, "traded": {"name": "Andrew Shaw", "age": 27.9, "war": 0.8, "points": 47}, "tradeId": "2019-06-30-MTL-CHI", "fullTrade": {"out": [{"name": "Andrew Shaw", "age": 27.9, "war": 0.8, "points": 47}], "outPicks": ["7th ('20)"], "in": [], "inPicks": ["2nd ('20)", "3rd ('21)"], "gaveUp": "MTL", "acquiredBy": "CHI"}, "gotBack": []}, {"name": "David Booth", "date": "2011-10-22", "season": "2011", "warAtTrade": 1.14, "ageAtTrade": 26.9, "gaveUp": "FLA", "acquiredBy": "VAN", "returnPlayers": ["Marco Sturm", "Mikael Samuelsson"], "returnPicks": [], "package": true, "retained": false, "capHit": 4250000, "yearsLeft": 4, "similar": 92, "returnValue": 0.18, "traded": {"name": "David Booth", "age": 26.9, "war": 1.2, "points": 41}, "tradeId": "2011-10-22-VAN-FLA", "fullTrade": {"out": [{"name": "David Booth", "age": 26.9, "war": 1.2, "points": 41}], "outPicks": ["3rd ('13)"], "in": [{"name": "Marco Sturm", "age": 33.1, "war": 0.1, "points": 16}, {"name": "Mikael Samuelsson", "age": 34.8, "war": 0.2, "points": 53}], "inPicks": [], "gaveUp": "FLA", "acquiredBy": "VAN"}, "gotBack": [{"name": "Marco Sturm", "age": 33.1, "war": 0.1, "points": 16}, {"name": "Mikael Samuelsson", "age": 34.8, "war": 0.2, "points": 53}]}, {"name": "Tomas Tatar", "date": "2018-02-26", "season": "2018", "warAtTrade": 0.44, "ageAtTrade": 27.2, "gaveUp": "DET", "acquiredBy": "VGK", "returnPlayers": [], "returnPicks": ["1st ('18)", "2nd ('19)"], "package": false, "retained": false, "capHit": 5300000, "yearsLeft": 4, "similar": 91, "returnValue": 1.33, "traded": {"name": "Tomas Tatar", "age": 27.2, "war": 3.1, "points": 52}, "tradeId": "2018-02-26-DET-VGK", "fullTrade": {"out": [{"name": "Tomas Tatar", "age": 27.2, "war": 3.1, "points": 52}], "outPicks": [], "in": [], "inPicks": ["1st ('18)", "2nd ('19)"], "gaveUp": "DET", "acquiredBy": "VGK"}, "gotBack": []}, {"name": "Mikkel Boedker", "date": "2018-06-19", "season": "2018", "warAtTrade": 0.35, "ageAtTrade": 28.5, "gaveUp": "SJS", "acquiredBy": "OTT", "returnPlayers": ["Mike Hoffman"], "returnPicks": [], "package": false, "retained": false, "capHit": 4000000, "yearsLeft": 3, "similar": 88, "returnValue": 2.04, "traded": {"name": "Mikkel Boedker", "age": 28.5, "war": 1.2, "points": 37}, "tradeId": "2018-06-19-SJS-OTT", "fullTrade": {"out": [{"name": "Mikkel Boedker", "age": 28.5, "war": 1.2, "points": 37}], "outPicks": [], "in": [{"name": "Mike Hoffman", "age": 28.6, "war": 3.9, "points": 56}], "inPicks": [], "gaveUp": "SJS", "acquiredBy": "OTT"}, "gotBack": [{"name": "Mike Hoffman", "age": 28.6, "war": 3.9, "points": 56}]}], "thin": false, "prodPct": 65, "estimate": 1.02, "negativeValue": false, "negNote": null, "note": "Real trades of players closest to him by PRODUCTION (points rank among same-season peers), age, contract AND years of control \u2014 so a controlled scorer matches other controlled scorers, not rentals. The return is only what his old team got back FROM the team that landed him; \u201cpackage\u201d means he wasn't the only piece going out, so that return isn't his alone. For the genuinely elite \u2014 who almost never trade, so their only comps are distressed sales \u2014 we show a MODELED estimate of what a player his caliber would command instead."}, "salaryDump": null, "fairContract": {"available": true, "age": 27, "valueWar": 0.8, "rate": 4710846, "terms": [{"years": 2, "endAge": 29, "projectedWar": [0.77, 0.73], "fairAav": 4308134, "totalValue": 8616269}, {"years": 3, "endAge": 30, "projectedWar": [0.77, 0.73, 0.69], "fairAav": 4213918, "totalValue": 12641753}, {"years": 4, "endAge": 31, "projectedWar": [0.77, 0.73, 0.69, 0.64], "fairAav": 4107924, "totalValue": 16431694}, {"years": 5, "endAge": 32, "projectedWar": [0.77, 0.73, 0.69, 0.64, 0.59], "fairAav": 3997219, "totalValue": 19986093}, {"years": 6, "endAge": 33, "projectedWar": [0.77, 0.73, 0.69, 0.64, 0.59, 0.53], "fairAav": 3876307, "totalValue": 23257841}, {"years": 7, "endAge": 34, "projectedWar": [0.77, 0.73, 0.69, 0.64, 0.59, 0.53, 0.47], "fairAav": 3749563, "totalValue": 26246939}, {"years": 8, "endAge": 35, "projectedWar": [0.77, 0.73, 0.69, 0.64, 0.59, 0.53, 0.47, 0.4], "fairAav": 3613285, "totalValue": 28906277}], "note": "Fair AAV = average projected annual market value over the term (aging-curve WAR walk x $4.71M/WAR, each year floored at the league minimum). Longer terms average in decline years, so the fair AAV falls. Real deals carry a term/security premium this does not model -- it is the production-fair anchor, not a prediction of the signing."}, "contractProjection": null, "contractAudit": null, "explain": {"scorecard": {"value": {"receipts": [{"label": "Even strength (5v5)", "value": "+1.44 WAR", "tone": "pos"}, {"label": "Special teams (PP + PK)", "value": "+0.08 WAR", "tone": "pos"}, {"label": "Penalty discipline (vs position)", "value": "+0.22 WAR", "tone": "pos"}, {"label": "Faceoffs", "value": "-0.22 WAR", "tone": "neg"}, {"label": "Total, last 3 seasons", "value": "+2.39 WAR", "tone": "pos", "strong": true}], "summary": "His total on-ice value, converted to WINS (WAR). It adds up everything he does \u2014 even-strength play, the power play and penalty kill, his penalty discipline RELATIVE TO HIS POSITION (defensemen structurally take more than they draw, so only the differential vs other D counts), and faceoffs \u2014 and the grade ranks that total against other players at his position over the last three seasons.", "method": "Total WAR sums these four, each priced in wins. The grade is this player's percentile vs same-position peers over the 3-season window."}, "overall": {"receipts": [{"label": "5v5 xG impact (RAPM)", "value": "+0.02 xG/60", "tone": "neutral", "strong": true}, {"label": "\u2014 offense", "value": "+0.02 xG/60", "tone": "neutral"}, {"label": "\u2014 defense", "value": "-0.01 xG/60", "tone": "neutral"}, {"label": "5v5 sample", "value": "2,868 min", "tone": "neutral"}, {"label": "On-ice xG share", "value": "45.2%", "tone": "neutral"}, {"label": "Relative to team (on \u2212 off ice)", "value": "-2.6%", "tone": "neg"}], "summary": "His two-way impact at 5-on-5: do his team's scoring chances go UP, and the other team's go DOWN, when he's on the ice? We isolate his effect from his linemates, the competition, and where his shifts start \u2014 so it's his fingerprint on the play, not just his teammates' work.", "method": "Teammate-, competition- and zone-start-adjusted 5v5 expected goals, via ridge regression over shift stints. An impact estimate, not a box score."}, "offense": {"receipts": [{"label": "Offensive xG impact (RAPM)", "value": "+0.02 xG/60", "tone": "neutral", "strong": true}, {"label": "On-ice xG created", "value": "39", "tone": "neutral"}, {"label": "Relative on-ice xG%", "value": "-2.6%", "tone": "neg"}], "summary": "His effect on the chances his team CREATES at 5-on-5 \u2014 how much shot-quality (expected goals) his line generates with him out there, after adjusting for who he plays with and against.", "method": "His share of 5v5 expected-goals creation, adjusted for who he plays with and against."}, "defense": {"receipts": [{"label": "Defensive xG impact (RAPM)", "value": "-0.01 xG/60", "tone": "neutral", "strong": true}, {"label": "On-ice xG allowed", "value": "47", "tone": "neutral"}], "summary": "His effect on the chances his team ALLOWS at 5-on-5 \u2014 how well shot-quality against is held down with him on the ice, after adjusting for teammates and competition. A higher grade means fewer good chances against.", "method": "His suppression of 5v5 expected goals against, teammate- and competition-adjusted. Higher means fewer chances allowed while he's on the ice."}, "ppOffense": {"receipts": [{"label": "Power-play xG impact (RAPM)", "value": "-0.03 xG/60", "tone": "neutral", "strong": true}, {"label": "PP ice time", "value": "115 min", "tone": "neutral"}], "summary": "His impact on the POWER PLAY \u2014 how much his team's chances improve with him on the man advantage, graded only against players who actually log power-play minutes (so a bottom-six grinder isn't penalized for never being out there).", "method": "Power-play expected-goals impact, RAPM-adjusted. Graded vs peers who actually play the PP."}, "pkDefense": {"receipts": [{"label": "Penalty-kill xG suppression (RAPM)", "value": "+0.04 xG/60", "tone": "neutral", "strong": true}, {"label": "PK ice time", "value": "72 min", "tone": "neutral"}], "summary": "His impact on the PENALTY KILL \u2014 how well his team smothers chances while short-handed with him on the ice, graded against other penalty-killers.", "method": "Penalty-kill expected-goals suppression, RAPM-adjusted."}, "finishing": {"receipts": [{"label": "Career shots", "value": "1,303", "tone": "neutral"}, {"label": "Goals", "value": "124", "tone": "neutral"}, {"label": "Goals above expected", "value": "+16.0", "tone": "pos"}, {"label": "True talent / 100 shots", "value": "+0.88", "tone": "pos", "strong": true}, {"label": "Reliability", "value": "72%", "tone": "neutral"}], "summary": "Whether he scores MORE goals than the quality of his shots would predict \u2014 pure finishing talent. We take his goals minus the expected goals on every shot of his career, then trust it more the more he's shot (a 2,000-shot sample is real; a 200-shot hot streak isn't yet).", "method": "Goals minus expected over career shots, then regressed to the mean by sample size. A high-volume shooter earns a more confident read (higher reliability)."}}, "skills": {"hits60": {"receipts": [{"label": "Physicality rate", "value": "0.74 / 60", "tone": "neutral"}], "method": "Per-60 rate over 3 seasons (TOI-weighted), ranked vs same-position peers.", "label": "Physicality", "summary": "Physicality is how often he throws a body check \u2014 counted straight from the NHL's play-by-play. He's logged 48 hits over his last 233 games (0.7 per 60 minutes on the ice), and the grade ranks that against other forwards.", "caveat": "Home-scorer count -- arena bias is real (some rinks record far more than others). Read big gaps as signal, small ones as noise."}, "blocks60": {"receipts": [{"label": "Shot blocking rate", "value": "1.64 / 60", "tone": "neutral"}], "method": "Per-60 rate over 3 seasons (TOI-weighted), ranked vs same-position peers.", "label": "Shot blocking", "summary": "Shot blocking is how willing he is to get in a shooting lane \u2014 counted straight from the NHL's play-by-play. He's logged 106 blocked shots over his last 233 games (1.6 per 60 minutes on the ice), and the grade ranks that against other forwards.", "caveat": "Home-scorer count -- arena bias is real (some rinks record far more than others). Read big gaps as signal, small ones as noise."}, "takeaways60": {"receipts": [{"label": "Puck stripping rate", "value": "1.08 / 60", "tone": "neutral"}], "method": "Per-60 rate over 3 seasons (TOI-weighted), ranked vs same-position peers.", "label": "Puck stripping", "summary": "Puck stripping is how often he strips the puck off an opponent \u2014 counted straight from the NHL's play-by-play. He's logged 70 takeaways over his last 233 games (1.1 per 60 minutes on the ice), and the grade ranks that against other forwards.", "caveat": "Home-scorer count -- arena bias is real (some rinks record far more than others). Read big gaps as signal, small ones as noise."}, "giveaways60": {"receipts": [{"label": "Puck security rate", "value": "2.24 / 60", "tone": "neutral"}, {"label": "Direction", "value": "fewer is better", "tone": "neutral"}], "method": "Per-60 rate over 3 seasons (TOI-weighted), ranked vs same-position peers.", "label": "Puck security", "summary": "Puck security is how often he turns the puck over (fewer is better) \u2014 counted straight from the NHL's play-by-play. He's logged 145 giveaways over his last 233 games (2.2 per 60 minutes on the ice), and the grade ranks that against other forwards.", "caveat": "Home-scorer count -- arena bias is real (some rinks record far more than others). Read big gaps as signal, small ones as noise."}, "primary_assists60": {"receipts": [{"label": "Playmaking rate", "value": "0.57 / 60", "tone": "neutral"}], "method": "Per-60 rate over 3 seasons (TOI-weighted), ranked vs same-position peers.", "label": "Playmaking", "summary": "Playmaking is how often he makes the primary pass on a goal \u2014 0.57 per 60 minutes of ice time over his last 3 seasons, ranked against other forwards."}, "rush_xg60": {"receipts": [{"label": "Rush offense rate", "value": "0.11 / 60", "tone": "neutral"}], "method": "Per-60 rate over 3 seasons (TOI-weighted), ranked vs same-position peers.", "label": "Rush offense", "summary": "Rush offense is the danger of the chances he creates off the rush \u2014 0.11 per 60 minutes of ice time over his last 3 seasons, ranked against other forwards."}}}, "projection": {"available": true, "asOfSeason": 20252026, "baseWar": 0.75, "years": [{"horizon": 1, "seasonId": 20262027, "age": 29.0, "projWar": 0.71, "lo": 0.14, "hi": 1.28}, {"horizon": 2, "seasonId": 20272028, "age": 30.0, "projWar": 0.67, "lo": 0.07, "hi": 1.27}, {"horizon": 3, "seasonId": 20282029, "age": 31.0, "projWar": 0.62, "lo": -0.01, "hi": 1.25}, {"horizon": 4, "seasonId": 20292030, "age": 32.0, "projWar": 0.57, "lo": -0.07, "hi": 1.21}, {"horizon": 5, "seasonId": 20302031, "age": 33.0, "projWar": 0.51, "lo": -0.15, "hi": 1.17}]}, "clause": {"hasNmc": false, "hasNtc": true, "noTradeListSize": 10, "label": "Modified NTC (10-team)", "terms": null, "details": "10 Team No Trade List"}, "trajectory": {"available": true, "direction": "down", "tier": "regression", "label": "Regression risk", "detail": "Priced on strong past seasons, but his current-season impact is well below that -- the value below may be propping him up.", "gap": -0.64, "currentWar": 0.16, "windowWar": 0.8, "currentSeason": 20252026}, "scorecard": {"offense": 53, "defense": 42, "overall": 48, "peers": 776, "window": "multi-year RAPM (recent 3 seasons)", "recent": {"offense": 27, "defense": 13, "overall": 12, "season": 20252026, "peers": 673}, "value": 78, "valueGroup": "F", "valueTrend": [{"season": 20222023, "pctl": 58}, {"season": 20232024, "pctl": 86}, {"season": 20242025, "pctl": 71}, {"season": 20252026, "pctl": 37}], "finishing": 81, "ppOffense": 59, "pkDefense": 67}, "skills": {"percentiles": {"hits60": 2.9, "blocks60": 29.2, "takeaways60": 44.3, "giveaways60": 49.9, "primary_assists60": 51.3, "rush_xg60": 71.3}, "window": "recent 3 seasons, TOI-weighted, vs position peers", "note": "hits/takeaways/giveaways are RTSS-tracked (arena scorer bias, not adjusted); giveaways shown as puck security (100 = fewest). All-situations TOI denominates rates.", "edge": {"season": 20252026, "maxSpeedMph": 21.9586, "maxSpeedPct": 36.8, "bursts22": 0, "bursts22Pct": 0.0, "bursts2022Pct": 52.3, "bursts1820Pct": 74.8, "distPer60Mi": 9.9317, "distPer60Pct": 79.5, "topGearPct": 18.4, "sustainedPct": 68.9, "speedPct": 48.7, "bySeason": [{"season": 20212022, "maxSpeedMph": 22.49, "maxSpeedPct": 67.3, "topGearPct": 68.2, "sustainedPct": 79.6, "speedPct": 75.0, "distPer60Mi": 9.9243, "distPer60Pct": 74.2}, {"season": 20222023, "maxSpeedMph": 21.701, "maxSpeedPct": 31.1, "topGearPct": 15.6, "sustainedPct": 69.6, "speedPct": 48.0, "distPer60Mi": 9.969, "distPer60Pct": 84.7}, {"season": 20232024, "maxSpeedMph": 22.336, "maxSpeedPct": 57.7, "topGearPct": 66.5, "sustainedPct": 79.6, "speedPct": 74.4, "distPer60Mi": 10.0801, "distPer60Pct": 89.9}, {"season": 20242025, "maxSpeedMph": 21.973, "maxSpeedPct": 37.3, "topGearPct": 18.6, "sustainedPct": 77.3, "speedPct": 53.8, "distPer60Mi": 10.1131, "distPer60Pct": 87.9}, {"season": 20252026, "maxSpeedMph": 21.9586, "maxSpeedPct": 36.8, "topGearPct": 18.4, "sustainedPct": 68.9, "speedPct": 48.7, "distPer60Mi": 9.9317, "distPer60Pct": 79.5}], "note": "NHL EDGE puck-and-player tracking; percentiles are league-wide for the season. Tracking starts 2021-22."}, "shot": {"season": 20252026, "topMph": 96.14, "topPct": 98.0, "avgMph": 56.605, "avgPct": 79.2, "over100": 0, "hardestDate": "2026-01-23", "hardestMatchup": "WSH@CGY", "note": "Raw puck speed (NHL EDGE) -- a physical tool, not a finishing grade."}, "context": {"season": 20252026, "competition": {"usagePct": 61.2, "prodPct": 69.8, "oppToiPg": 17.752}, "teammates": {"usagePct": 61.2, "prodPct": 20.5, "tmToiPg": 17.8552}, "note": "From shift overlaps. Headline is usage (ice time of the players around him); production is the model's grade of those players. A big gap means leaned-on help that grades below its minutes."}}, "comparables": {"available": true, "player": {"id": 8481068, "name": "Yegor Sharangovich", "group": "F"}, "atAge": 27, "season": 20252026, "warAt": 0.16, "heightIn": 74, "weightLb": 196, "speedPct": 36.8, "windowAges": [23, 24, 25, 26, 27], "warSlots": [1.24, 0.48, 1.43, 0.8, 0.16], "comps": [{"name": "Alex Killorn", "age": 27, "season": 20162017, "distance": 0.193, "similarity": 95, "warAt": 0.39, "heightIn": 73, "weightLb": 205, "speedPct": null, "warSlots": [0.77, 0.33, 1.25, 0.76, 0.39], "nextWars": [1.14, 0.84, -0.05], "next3War": 1.9, "next3Known": 3, "why": {"close": ["off/def tilt", "playmaking"], "far": {"axis": "rush offense", "note": "less rush offense", "gapZ": 1.14}, "axes": [{"axis": "off/def tilt", "gapZ": 0.01, "note": "similar"}, {"axis": "playmaking", "gapZ": 0.04, "note": "similar"}, {"axis": "production arc", "gapZ": 0.26, "note": "similar"}, {"axis": "takeaways", "gapZ": 0.3, "note": "fewer takeaways"}, {"axis": "role (minutes)", "gapZ": 0.44, "note": "bigger minutes"}, {"axis": "size", "gapZ": 0.52, "note": "similar"}, {"axis": "physicality", "gapZ": 0.76, "note": "more physical"}, {"axis": "rush offense", "gapZ": 1.14, "note": "less rush offense"}]}}, {"name": "Melker Karlsson", "age": 27, "season": 20172018, "distance": 0.315, "similarity": 91, "warAt": -0.24, "heightIn": 72, "weightLb": 180, "speedPct": null, "warSlots": [null, 0.53, 1.04, 0.55, -0.24], "nextWars": [-0.2, -0.39], "next3War": -0.6, "next3Known": 2, "why": {"close": ["takeaways", "production arc"], "far": {"axis": "physicality", "note": "more physical", "gapZ": 1.12}, "axes": [{"axis": "takeaways", "gapZ": 0.08, "note": "similar"}, {"axis": "production arc", "gapZ": 0.37, "note": "lighter arc"}, {"axis": "off/def tilt", "gapZ": 0.41, "note": "more defense-tilted"}, {"axis": "role (minutes)", "gapZ": 0.44, "note": "smaller minutes"}, {"axis": "rush offense", "gapZ": 0.48, "note": "less rush offense"}, {"axis": "playmaking", "gapZ": 0.82, "note": "less playmaking"}, {"axis": "size", "gapZ": 0.99, "note": "smaller"}, {"axis": "physicality", "gapZ": 1.12, "note": "more physical"}]}}, {"name": "Adam Henrique", "age": 27, "season": 20172018, "distance": 0.319, "similarity": 91, "warAt": -0.07, "heightIn": 72, "weightLb": 195, "speedPct": null, "warSlots": [0.77, 0.78, 0.93, 0.48, -0.07], "nextWars": [0.61, 1.24, 0.73], "next3War": 2.6, "next3Known": 3, "why": {"close": ["role (minutes)", "playmaking"], "far": {"axis": "off/def tilt", "note": "more attack-tilted", "gapZ": 0.97}, "axes": [{"axis": "role (minutes)", "gapZ": 0.24, "note": "similar"}, {"axis": "playmaking", "gapZ": 0.27, "note": "less playmaking"}, {"axis": "takeaways", "gapZ": 0.3, "note": "more takeaways"}, {"axis": "production arc", "gapZ": 0.47, "note": "lighter arc"}, {"axis": "physicality", "gapZ": 0.57, "note": "more physical"}, {"axis": "rush offense", "gapZ": 0.57, "note": "less rush offense"}, {"axis": "size", "gapZ": 0.62, "note": "smaller"}, {"axis": "off/def tilt", "gapZ": 0.97, "note": "more attack-tilted"}]}}, {"name": "Sonny Milano", "age": 27, "season": 20232024, "distance": 0.339, "similarity": 91, "warAt": 0.49, "heightIn": 72, "weightLb": 205, "speedPct": 72.7, "warSlots": [0.59, null, 1.34, 0.77, 0.49], "nextWars": [], "next3War": null, "next3Known": 0, "why": {"close": ["production arc", "physicality"], "far": {"axis": "role (minutes)", "note": "smaller minutes", "gapZ": 1.45}, "axes": [{"axis": "production arc", "gapZ": 0.33, "note": "similar"}, {"axis": "physicality", "gapZ": 0.34, "note": "more physical"}, {"axis": "off/def tilt", "gapZ": 0.39, "note": "more attack-tilted"}, {"axis": "takeaways", "gapZ": 0.49, "note": "more takeaways"}, {"axis": "playmaking", "gapZ": 0.54, "note": "more playmaking"}, {"axis": "size", "gapZ": 0.82, "note": "smaller"}, {"axis": "rush offense", "gapZ": 0.85, "note": "less rush offense"}, {"axis": "role (minutes)", "gapZ": 1.45, "note": "smaller minutes"}]}}, {"name": "Colin Wilson", "age": 27, "season": 20162017, "distance": 0.355, "similarity": 90, "warAt": 0.39, "heightIn": 73, "weightLb": 215, "speedPct": null, "warSlots": [0.5, 0.59, 1.28, 0.48, 0.39], "nextWars": [0.51, 0.29], "next3War": 0.8, "next3Known": 2, "why": {"close": ["takeaways", "role (minutes)"], "far": {"axis": "rush offense", "note": "less rush offense", "gapZ": 1.3}, "axes": [{"axis": "takeaways", "gapZ": 0.06, "note": "similar"}, {"axis": "role (minutes)", "gapZ": 0.28, "note": "smaller minutes"}, {"axis": "production arc", "gapZ": 0.38, "note": "similar"}, {"axis": "physicality", "gapZ": 0.53, "note": "more physical"}, {"axis": "off/def tilt", "gapZ": 0.56, "note": "more attack-tilted"}, {"axis": "size", "gapZ": 0.77, "note": "similar"}, {"axis": "playmaking", "gapZ": 0.81, "note": "more playmaking"}, {"axis": "rush offense", "gapZ": 1.3, "note": "less rush offense"}]}}, {"name": "Valeri Nichushkin", "age": 27, "season": 20222023, "distance": 0.362, "similarity": 90, "warAt": 0.48, "heightIn": 76, "weightLb": 210, "speedPct": 97.4, "warSlots": [0.76, 1.15, 1.71, 0.62, 0.48], "nextWars": [0.28, -0.21, 1.02], "next3War": 1.1, "next3Known": 3, "why": {"close": ["playmaking", "rush offense"], "far": {"axis": "physicality", "note": "more physical", "gapZ": 1.12}, "axes": [{"axis": "playmaking", "gapZ": 0.11, "note": "similar"}, {"axis": "rush offense", "gapZ": 0.13, "note": "similar"}, {"axis": "off/def tilt", "gapZ": 0.29, "note": "more defense-tilted"}, {"axis": "production arc", "gapZ": 0.48, "note": "similar"}, {"axis": "takeaways", "gapZ": 0.84, "note": "more takeaways"}, {"axis": "role (minutes)", "gapZ": 0.85, "note": "smaller minutes"}, {"axis": "size", "gapZ": 0.94, "note": "bigger"}, {"axis": "physicality", "gapZ": 1.12, "note": "more physical"}]}}, {"name": "Michael Amadio", "age": 27, "season": 20232024, "distance": 0.364, "similarity": 90, "warAt": 0.67, "heightIn": 73, "weightLb": 206, "speedPct": 55.8, "warSlots": [1.03, null, 1.17, 0.56, 0.67], "nextWars": [0.71, 0.99], "next3War": 1.7, "next3Known": 2, "why": {"close": ["role (minutes)", "production arc"], "far": {"axis": "takeaways", "note": "more takeaways", "gapZ": 1.28}, "axes": [{"axis": "role (minutes)", "gapZ": 0.31, "note": "smaller minutes"}, {"axis": "production arc", "gapZ": 0.42, "note": "similar"}, {"axis": "off/def tilt", "gapZ": 0.43, "note": "more defense-tilted"}, {"axis": "size", "gapZ": 0.55, "note": "similar"}, {"axis": "physicality", "gapZ": 0.6, "note": "more physical"}, {"axis": "playmaking", "gapZ": 0.71, "note": "less playmaking"}, {"axis": "rush offense", "gapZ": 0.91, "note": "less rush offense"}, {"axis": "takeaways", "gapZ": 1.28, "note": "more takeaways"}]}}, {"name": "Artturi Lehkonen", "age": 27, "season": 20222023, "distance": 0.379, "similarity": 89, "warAt": 0.34, "heightIn": 71, "weightLb": 179, "speedPct": 83.3, "warSlots": [0.97, 0.53, 0.66, 1.07, 0.34], "nextWars": [0.43, 0.21, 0.43], "next3War": 1.1, "next3Known": 3, "why": {"close": ["off/def tilt", "role (minutes)"], "far": {"axis": "physicality", "note": "more physical", "gapZ": 1.36}, "axes": [{"axis": "off/def tilt", "gapZ": 0.02, "note": "similar"}, {"axis": "role (minutes)", "gapZ": 0.19, "note": "similar"}, {"axis": "playmaking", "gapZ": 0.24, "note": "similar"}, {"axis": "takeaways", "gapZ": 0.28, "note": "fewer takeaways"}, {"axis": "rush offense", "gapZ": 0.38, "note": "more rush offense"}, {"axis": "production arc", "gapZ": 0.41, "note": "similar"}, {"axis": "size", "gapZ": 1.32, "note": "smaller"}, {"axis": "physicality", "gapZ": 1.36, "note": "more physical"}]}}, {"name": "Artem Anisimov", "age": 27, "season": 20152016, "distance": 0.386, "similarity": 89, "warAt": -0.61, "heightIn": 76, "weightLb": 199, "speedPct": null, "warSlots": [1.37, 0.22, 0.68, 0.68, -0.61], "nextWars": [-0.5, -0.63, -0.05], "next3War": -1.2, "next3Known": 3, "why": {"close": ["playmaking", "role (minutes)"], "far": null, "axes": [{"axis": "playmaking", "gapZ": 0.15, "note": "similar"}, {"axis": "role (minutes)", "gapZ": 0.36, "note": "bigger minutes"}, {"axis": "physicality", "gapZ": 0.39, "note": "more physical"}, {"axis": "takeaways", "gapZ": 0.4, "note": "more takeaways"}, {"axis": "off/def tilt", "gapZ": 0.48, "note": "more attack-tilted"}, {"axis": "production arc", "gapZ": 0.57, "note": "lighter arc"}, {"axis": "size", "gapZ": 0.67, "note": "bigger"}, {"axis": "rush offense", "gapZ": 0.75, "note": "less rush offense"}]}}, {"name": "Ryan Poehling", "age": 27, "season": 20252026, "distance": 0.389, "similarity": 89, "warAt": 0.01, "heightIn": 74, "weightLb": 206, "speedPct": 88.3, "warSlots": [0.27, 0.52, 0.98, 0.08, 0.01], "nextWars": [], "next3War": null, "next3Known": 0, "why": {"close": ["off/def tilt", "size"], "far": null, "axes": [{"axis": "off/def tilt", "gapZ": 0.24, "note": "similar"}, {"axis": "size", "gapZ": 0.25, "note": "similar"}, {"axis": "takeaways", "gapZ": 0.34, "note": "fewer takeaways"}, {"axis": "role (minutes)", "gapZ": 0.36, "note": "smaller minutes"}, {"axis": "playmaking", "gapZ": 0.4, "note": "more playmaking"}, {"axis": "production arc", "gapZ": 0.58, "note": "lighter arc"}, {"axis": "physicality", "gapZ": 0.61, "note": "more physical"}, {"axis": "rush offense", "gapZ": 0.69, "note": "less rush offense"}]}}, {"name": "Chandler Stephenson", "age": 27, "season": 20212022, "distance": 0.406, "similarity": 89, "warAt": -0.04, "heightIn": 72, "weightLb": 201, "speedPct": 94.2, "warSlots": [0.32, 0.5, 0.82, 0.34, -0.04], "nextWars": [1.32, -0.21, -1.06], "next3War": 0.1, "next3Known": 3, "why": {"close": ["playmaking", "off/def tilt"], "far": {"axis": "rush offense", "note": "less rush offense", "gapZ": 1.09}, "axes": [{"axis": "playmaking", "gapZ": 0.15, "note": "similar"}, {"axis": "off/def tilt", "gapZ": 0.17, "note": "similar"}, {"axis": "takeaways", "gapZ": 0.35, "note": "more takeaways"}, {"axis": "physicality", "gapZ": 0.53, "note": "more physical"}, {"axis": "production arc", "gapZ": 0.55, "note": "lighter arc"}, {"axis": "role (minutes)", "gapZ": 0.59, "note": "bigger minutes"}, {"axis": "size", "gapZ": 0.72, "note": "smaller"}, {"axis": "rush offense", "gapZ": 1.09, "note": "less rush offense"}]}}, {"name": "Calle Jarnkrok", "age": 27, "season": 20182019, "distance": 0.409, "similarity": 89, "warAt": 0.86, "heightIn": 72, "weightLb": 193, "speedPct": null, "warSlots": [1.05, 0.11, 1.39, 0.52, 0.86], "nextWars": [1.19, 1.07, 0.06], "next3War": 2.3, "next3Known": 3, "why": {"close": ["role (minutes)", "physicality"], "far": {"axis": "rush offense", "note": "less rush offense", "gapZ": 1.39}, "axes": [{"axis": "role (minutes)", "gapZ": 0.02, "note": "similar"}, {"axis": "physicality", "gapZ": 0.35, "note": "more physical"}, {"axis": "production arc", "gapZ": 0.44, "note": "similar"}, {"axis": "takeaways", "gapZ": 0.51, "note": "fewer takeaways"}, {"axis": "off/def tilt", "gapZ": 0.6, "note": "more defense-tilted"}, {"axis": "size", "gapZ": 0.67, "note": "smaller"}, {"axis": "playmaking", "gapZ": 0.82, "note": "less playmaking"}, {"axis": "rush offense", "gapZ": 1.39, "note": "less rush offense"}]}}], "compsMedianNext3": 1.9, "compsSpreadNext3": [1.1, 2.5], "compsBand": {"half": 1.3, "lo": 0.6, "hi": 3.2, "confidence": "ok", "understates": false}, "curveNext3": 0.3, "honesty": "Comps match career-through-age shape (WAR trajectory, role, off/def split, skill shape, size) within the same position group and exact age. The payoff column is what each comp ACTUALLY did over his next three seasons -- a tendency, not a destiny; the spread is the message. Weights chosen not fit; --backtest reports what they buy."}, "playoffs": null, "recentMove": null, "meta": {"war": "Total WAR = EV (5v5 RAPM) + special teams + penalties + faceoffs + finishing. xG-based play-driving plus shrunk shooting talent; single-season RAPM is noisy -- the pooled multi-year RAPM is the stable read.", "rapm": "off/def/total RAPM are net xG per 60 at 5v5, teammate- and competition-adjusted (ridge regression over shift stints).", "coverage": "On-ice metrics cover seasons with shift data: 2010-11 to present (100% of regular-season games).", "asOf": "2026-06-09"}, "_explain": {"available": true, "player": {"id": 8481068, "name": "Yegor Sharangovich"}, "season": 20252026, "seasonLabel": "2025-26", "totalWar": 0.16, "totalPercentile": 38, "components": [{"name": "even-strength play (5v5)", "war": -0.14, "percentile": 10}, {"name": "special teams (PP/PK)", "war": -0.0, "percentile": 36}, {"name": "finishing (shooting talent)", "war": 0.27, "percentile": 86}, {"name": "penalty discipline (vs position)", "war": 0.08, "percentile": 69}, {"name": "faceoffs", "war": -0.05, "percentile": 9}], "summary": "Yegor Sharangovich's +0.16 total WAR in 2025-26 ranks in the 38th percentile of NHL skaters. It breaks down as: even-strength play (5v5): -0.14 WAR (10th percentile); special teams (PP/PK): -0.00 WAR (36th percentile); finishing (shooting talent): +0.27 WAR (86th percentile); penalty discipline (vs position): +0.08 WAR (69th percentile); faceoffs: -0.05 WAR (9th percentile).", "narrative": "Yegor Sharangovich's +0.16 WAR in 2025-26 is driven most by finishing (shooting talent) (+0.27, 86th percentile) -- within 5v5 he tilts toward offense (offense -0.08/60, 27th percentile; defense -0.13/60, 13th percentile). His weakest area is even-strength play (5v5) (-0.14, 10th percentile). (xG-based; single-season RAPM is noisy -- see multi-year RAPM for the stable read.)"}}