{"20182019": [{"x": 41.0, "y": -11.0, "xg": 0.0572, "goal": false, "type": "snap", "rebound": false, "rush": true}, {"x": 78.0, "y": -6.0, "xg": 0.2192, "goal": false, "type": "slap", "rebound": false, "rush": true}, {"x": 51.0, "y": 14.0, "xg": 0.0497, "goal": false, "type": "snap", "rebound": false, "rush": false}, {"x": 39.0, "y": 23.0, "xg": 0.0225, "goal": false, "type": "slap", "rebound": false, "rush": false}, {"x": 53.0, "y": 29.0, "xg": 0.0295, "goal": false, "type": "slap", "rebound": false, "rush": false}, {"x": 59.0, "y": 3.0, "xg": 0.0529, "goal": false, "type": "snap", "rebound": false, "rush": false}, {"x": 50.0, "y": -8.0, "xg": 0.0439, "goal": false, "type": "snap", "rebound": false, "rush": false}, {"x": 69.0, "y": -8.0, "xg": 0.1182, "goal": false, "type": "wrist", "rebound": false, "rush": true}, {"x": 67.0, "y": 8.0, "xg": 0.1407, "goal": false, "type": "snap", "rebound": false, "rush": true}, {"x": 45.0, "y": 13.0, "xg": 0.0243, "goal": false, "type": "wrist", "rebound": false, "rush": false}, {"x": 63.0, "y": 16.0, "xg": 0.1309, "goal": false, "type": "snap", "rebound": false, "rush": false}, {"x": 56.0, "y": -35.0, "xg": 0.0212, "goal": false, "type": "wrist", "rebound": false, "rush": false}, {"x": 39.0, "y": 24.0, "xg": 0.0316, "goal": false, "type": "wrist", "rebound": false, "rush": false}, {"x": 85.0, "y": 25.0, "xg": 0.0159, "goal": false, "type": "wrist", "rebound": false, "rush": false}, {"x": 78.0, "y": 9.0, "xg": 0.0403, "goal": false, "type": "wrist", "rebound": false, "rush": false}, {"x": 42.0, "y": 32.0, "xg": 0.0563, "goal": false, "type": "slap", "rebound": true, "rush": false}, {"x": 49.0, "y": -14.0, "xg": 0.0285, "goal": false, "type": "backhand", "rebound": false, "rush": false}, {"x": 64.0, "y": -3.0, "xg": 0.0758, "goal": false, "type": "snap", "rebound": false, "rush": false}, {"x": 53.0, "y": 22.0, "xg": 0.054, "goal": false, "type": "snap", "rebound": false, "rush": true}, {"x": 86.0, "y": -7.0, "xg": 0.0757, "goal": false, "type": "backhand", "rebound": false, "rush": false}, {"x": 86.0, "y": -7.0, "xg": 0.0333, "goal": false, "type": "wrap-around", "rebound": false, "rush": false}, {"x": 79.0, "y": -19.0, "xg": 0.0328, "goal": false, "type": "backhand", "rebound": false, "rush": false}, {"x": 81.0, "y": -9.0, "xg": 0.0367, "goal": false, "type": "backhand", "rebound": false, "rush": false}, {"x": 83.0, "y": 4.0, "xg": 0.1769, "goal": false, "type": "deflected", "rebound": true, "rush": false}, {"x": 28.0, "y": 2.0, "xg": 0.0214, "goal": false, "type": "snap", "rebound": false, "rush": false}, {"x": 42.0, "y": -22.0, "xg": 0.0343, "goal": false, "type": "slap", "rebound": false, "rush": false}, {"x": 76.0, "y": -1.0, "xg": 0.0346, "goal": false, "type": "tip-in", "rebound": false, "rush": false}, {"x": 69.0, "y": 11.0, "xg": 0.0188, "goal": false, "type": "wrist", "rebound": false, "rush": false}, {"x": 52.0, "y": 9.0, "xg": 0.09, "goal": false, "type": "slap", "rebound": false, "rush": false}, {"x": 70.0, "y": -10.0, "xg": 0.0441, "goal": false, "type": "backhand", "rebound": false, "rush": false}, {"x": 70.0, "y": -21.0, "xg": 0.0445, "goal": false, "type": "backhand", "rebound": false, "rush": true}, {"x": 59.0, "y": -36.0, "xg": 0.0415, "goal": false, "type": "snap", "rebound": false, "rush": false}, {"x": 74.0, "y": -12.0, "xg": 0.1172, "goal": false, "type": "wrist", "rebound": false, "rush": false}, {"x": 76.0, "y": -8.0, "xg": 0.0263, "goal": false, "type": "tip-in", "rebound": false, "rush": false}, {"x": 27.0, "y": -3.0, "xg": 0.0149, "goal": false, "type": "deflected", "rebound": false, "rush": false}, {"x": 76.0, "y": 40.0, "xg": 0.017, "goal": false, "type": "snap", "rebound": false, "rush": false}, {"x": 54.0, "y": -21.0, "xg": 0.0686, "goal": false, "type": "snap", "rebound": false, "rush": false}, {"x": 53.0, "y": 14.0, "xg": 0.0329, "goal": false, "type": "wrist", "rebound": false, "rush": false}, {"x": 52.0, "y": 22.0, "xg": 0.0124, "goal": false, "type": "wrist", "rebound": false, "rush": false}, {"x": 82.0, "y": -5.0, "xg": 0.0688, "goal": false, "type": "tip-in", "rebound": false, "rush": false}, {"x": 85.0, "y": 14.0, "xg": 0.0571, "goal": false, "type": "wrist", "rebound": false, "rush": false}, {"x": 49.0, "y": -27.0, "xg": 0.0215, "goal": false, "type": "slap", "rebound": false, "rush": false}, {"x": 21.0, "y": 28.0, "xg": 0.0177, "goal": false, "type": "slap", "rebound": false, "rush": false}, {"x": 78.0, "y": -2.0, "xg": 0.1037, "goal": false, "type": "backhand", "rebound": false, "rush": true}, {"x": 81.0, "y": -6.0, "xg": 0.0284, "goal": false, "type": "tip-in", "rebound": false, "rush": false}, {"x": 42.0, "y": 2.0, "xg": 0.0294, "goal": false, "type": "wrist", "rebound": false, "rush": false}, {"x": 78.0, "y": -8.0, "xg": 0.0971, "goal": false, "type": "tip-in", "rebound": false, "rush": true}, {"x": 79.0, "y": -16.0, "xg": 0.0764, "goal": false, "type": "wrist", "rebound": false, "rush": false}, {"x": 80.0, "y": -9.0, "xg": 0.063, "goal": false, "type": "backhand", "rebound": false, "rush": false}, {"x": 76.0, "y": 2.0, "xg": 0.1673, "goal": false, "type": "wrist", "rebound": false, "rush": false}, {"x": 61.0, "y": 31.0, "xg": 0.026, "goal": false, "type": "wrist", "rebound": false, "rush": false}, {"x": 74.0, "y": 1.0, "xg": 0.1024, "goal": false, "type": "tip-in", "rebound": false, "rush": false}, {"x": 81.0, "y": -1.0, "xg": 0.1386, "goal": false, "type": "backhand", "rebound": false, "rush": false}, {"x": 37.0, "y": 36.0, "xg": 0.0196, "goal": false, "type": "wrist", "rebound": false, "rush": false}], "20202021": [{"x": 67.0, "y": 4.0, "xg": 0.0435, "goal": false, "type": "backhand", "rebound": false, "rush": false}, {"x": 93.0, "y": 22.0, "xg": 0.003, "goal": false, "type": "wrist", "rebound": false, "rush": false}, {"x": 87.0, "y": -21.0, "xg": 0.014, "goal": true, "type": "backhand", "rebound": false, "rush": false}, {"x": 81.0, "y": 7.0, "xg": 0.1845, "goal": false, "type": "snap", "rebound": false, "rush": true}, {"x": 58.0, "y": 6.0, "xg": 0.0524, "goal": false, "type": "wrist", "rebound": false, "rush": false}, {"x": 88.0, "y": -6.0, "xg": 0.021, "goal": false, "type": "wrap-around", "rebound": false, "rush": false}, {"x": 63.0, "y": 31.0, "xg": 0.0309, "goal": false, "type": "wrist", "rebound": false, "rush": false}, {"x": 58.0, "y": 1.0, "xg": 0.0526, "goal": false, "type": "wrist", "rebound": false, "rush": false}, {"x": 63.0, "y": -7.0, "xg": 0.0707, "goal": true, "type": "wrist", "rebound": false, "rush": false}, {"x": 58.0, "y": 29.0, "xg": 0.0421, "goal": false, "type": "wrist", "rebound": false, "rush": false}, {"x": 85.0, "y": -7.0, "xg": 0.2255, "goal": false, "type": "wrist", "rebound": false, "rush": true}, {"x": 59.0, "y": 7.0, "xg": 0.0605, "goal": false, "type": "wrist", "rebound": false, "rush": false}, {"x": 49.0, "y": 30.0, "xg": 0.0389, "goal": false, "type": "slap", "rebound": false, "rush": true}, {"x": 71.0, "y": -12.0, "xg": 0.0378, "goal": false, "type": "backhand", "rebound": false, "rush": false}, {"x": 72.0, "y": -27.0, "xg": 0.0663, "goal": false, "type": "wrist", "rebound": false, "rush": false}, {"x": 73.0, "y": -28.0, "xg": 0.0481, "goal": false, "type": "wrist", "rebound": false, "rush": false}, {"x": 76.0, "y": -3.0, "xg": 0.0747, "goal": false, "type": "tip-in", "rebound": false, "rush": false}, {"x": 73.0, "y": -0.0, "xg": 0.155, "goal": false, "type": "slap", "rebound": false, "rush": false}, {"x": 86.0, "y": 7.0, "xg": 0.1757, "goal": false, "type": "wrist", "rebound": true, "rush": false}, {"x": 71.0, "y": -17.0, "xg": 0.0343, "goal": true, "type": "backhand", "rebound": false, "rush": false}, {"x": 85.0, "y": -5.0, "xg": 0.0346, "goal": false, "type": "wrap-around", "rebound": false, "rush": false}, {"x": 68.0, "y": 32.0, "xg": 0.0318, "goal": false, "type": "snap", "rebound": false, "rush": false}, {"x": 42.0, "y": 19.0, "xg": 0.024, "goal": false, "type": "snap", "rebound": false, "rush": false}, {"x": 51.0, "y": -20.0, "xg": 0.0389, "goal": false, "type": "slap", "rebound": false, "rush": false}, {"x": 84.0, "y": 5.0, "xg": 0.1562, "goal": false, "type": "backhand", "rebound": true, "rush": false}, {"x": 50.0, "y": 23.0, "xg": 0.0199, "goal": false, "type": "wrist", "rebound": false, "rush": false}, {"x": 33.0, "y": -3.0, "xg": 0.0299, "goal": false, "type": "slap", "rebound": false, "rush": false}, {"x": 81.0, "y": -11.0, "xg": 0.0721, "goal": false, "type": "wrist", "rebound": false, "rush": false}, {"x": 71.0, "y": -18.0, "xg": 0.0378, "goal": false, "type": "backhand", "rebound": false, "rush": false}, {"x": 79.0, "y": 1.0, "xg": 0.109, "goal": false, "type": "tip-in", "rebound": false, "rush": false}, {"x": 81.0, "y": -6.0, "xg": 0.0359, "goal": false, "type": "wrap-around", "rebound": false, "rush": false}, {"x": 80.0, "y": -12.0, "xg": 0.0423, "goal": false, "type": "tip-in", "rebound": false, "rush": false}, {"x": 82.0, "y": -6.0, "xg": 0.0517, "goal": false, "type": "wrap-around", "rebound": false, "rush": false}, {"x": 79.0, "y": -1.0, "xg": 0.092, "goal": false, "type": "wrist", "rebound": false, "rush": false}, {"x": 60.0, "y": 37.0, "xg": 0.0257, "goal": false, "type": "wrist", "rebound": false, "rush": false}, {"x": 43.0, "y": -19.0, "xg": 0.0354, "goal": false, "type": "wrist", "rebound": false, "rush": false}, {"x": 53.0, "y": 16.0, "xg": 0.0457, "goal": false, "type": "wrist", "rebound": false, "rush": false}, {"x": 72.0, "y": -13.0, "xg": 0.0592, "goal": false, "type": "wrist", "rebound": false, "rush": false}, {"x": 82.0, "y": -3.0, "xg": 0.1664, "goal": false, "type": "slap", "rebound": false, "rush": false}, {"x": 85.0, "y": 25.0, "xg": 0.0293, "goal": false, "type": "wrist", "rebound": false, "rush": false}, {"x": 59.0, "y": 15.0, "xg": 0.0993, "goal": false, "type": "snap", "rebound": false, "rush": false}, {"x": 49.0, "y": 15.0, "xg": 0.0554, "goal": false, "type": "slap", "rebound": false, "rush": false}, {"x": 80.0, "y": 1.0, "xg": 0.1546, "goal": false, "type": "tip-in", "rebound": true, "rush": false}, {"x": 62.0, "y": 18.0, "xg": 0.0449, "goal": false, "type": "wrist", "rebound": false, "rush": false}, {"x": 65.0, "y": -22.0, "xg": 0.0779, "goal": false, "type": "wrist", "rebound": false, "rush": false}, {"x": 53.0, "y": 24.0, "xg": 0.0261, "goal": false, "type": "wrist", "rebound": false, "rush": false}, {"x": 69.0, "y": -14.0, "xg": 0.1502, "goal": false, "type": "wrist", "rebound": false, "rush": true}, {"x": 40.0, "y": -2.0, "xg": 0.0313, "goal": false, "type": "wrist", "rebound": false, "rush": false}, {"x": 71.0, "y": 10.0, "xg": 0.1274, "goal": false, "type": "wrist", "rebound": false, "rush": false}, {"x": 32.0, "y": -4.0, "xg": 0.0613, "goal": false, "type": "wrist", "rebound": false, "rush": true}, {"x": 41.0, "y": 24.0, "xg": 0.0133, "goal": false, "type": "wrist", "rebound": false, "rush": false}, {"x": 50.0, "y": 28.0, "xg": 0.0286, "goal": false, "type": "snap", "rebound": false, "rush": false}, {"x": 73.0, "y": -2.0, "xg": 0.1278, "goal": false, "type": "deflected", "rebound": false, "rush": true}, {"x": 77.0, "y": -9.0, "xg": 0.0886, "goal": false, "type": "wrist", "rebound": false, "rush": false}, {"x": 83.0, "y": -4.0, "xg": 0.0483, "goal": true, "type": "wrap-around", "rebound": false, "rush": true}, {"x": 53.0, "y": 25.0, "xg": 0.0683, "goal": false, "type": "slap", "rebound": false, "rush": false}, {"x": 41.0, "y": -29.0, "xg": 0.0303, "goal": false, "type": "slap", "rebound": false, "rush": false}], "20212022": [{"x": 80.0, "y": -1.0, "xg": 0.0948, "goal": false, "type": "backhand", "rebound": false, "rush": false}, {"x": 74.0, "y": 11.0, "xg": 0.0452, "goal": false, "type": "tip-in", "rebound": false, "rush": false}, {"x": 51.0, "y": 29.0, "xg": 0.0237, "goal": false, "type": "wrist", "rebound": false, "rush": false}, {"x": 85.0, "y": 6.0, "xg": 0.0975, "goal": false, "type": "backhand", "rebound": true, "rush": false}, {"x": 42.0, "y": 13.0, "xg": 0.0524, "goal": false, "type": "wrist", "rebound": false, "rush": true}, {"x": 43.0, "y": -27.0, "xg": 0.0284, "goal": false, "type": "wrist", "rebound": false, "rush": false}, {"x": 64.0, "y": 23.0, "xg": 0.0806, "goal": false, "type": "wrist", "rebound": false, "rush": true}, {"x": 64.0, "y": 3.0, "xg": 0.1085, "goal": false, "type": "snap", "rebound": false, "rush": false}, {"x": 56.0, "y": -25.0, "xg": 0.0241, "goal": false, "type": "wrist", "rebound": false, "rush": false}, {"x": 38.0, "y": 22.0, "xg": 0.012, "goal": false, "type": "wrist", "rebound": false, "rush": false}, {"x": 44.0, "y": -31.0, "xg": 0.0095, "goal": false, "type": "wrist", "rebound": false, "rush": false}, {"x": 43.0, "y": 22.0, "xg": 0.0189, "goal": false, "type": "slap", "rebound": false, "rush": false}, {"x": 62.0, "y": -27.0, "xg": 0.0113, "goal": false, "type": "backhand", "rebound": false, "rush": false}, {"x": 63.0, "y": -16.0, "xg": 0.0601, "goal": false, "type": "backhand", "rebound": false, "rush": false}, {"x": 66.0, "y": 18.0, "xg": 0.0747, "goal": false, "type": "snap", "rebound": false, "rush": false}, {"x": 75.0, "y": 1.0, "xg": 0.272, "goal": false, "type": "wrist", "rebound": true, "rush": false}, {"x": 57.0, "y": 15.0, "xg": 0.0594, "goal": false, "type": "snap", "rebound": false, "rush": false}, {"x": 65.0, "y": -1.0, "xg": 0.1114, "goal": false, "type": "wrist", "rebound": false, "rush": true}, {"x": 70.0, "y": 12.0, "xg": 0.0876, "goal": true, "type": "wrist", "rebound": false, "rush": false}, {"x": 67.0, "y": -28.0, "xg": 0.0123, "goal": false, "type": "backhand", "rebound": false, "rush": false}, {"x": 53.0, "y": 24.0, "xg": 0.036, "goal": false, "type": "snap", "rebound": false, "rush": false}, {"x": 75.0, "y": -0.0, "xg": 0.2284, "goal": false, "type": "wrist", "rebound": true, "rush": false}, {"x": 48.0, "y": 13.0, "xg": 0.067, "goal": false, "type": "wrist", "rebound": false, "rush": true}, {"x": 61.0, "y": 27.0, "xg": 0.0385, "goal": false, "type": "wrist", "rebound": false, "rush": false}, {"x": 73.0, "y": -3.0, "xg": 0.1955, "goal": true, "type": "wrist", "rebound": true, "rush": false}, {"x": 5.0, "y": -4.0, "xg": 0.0106, "goal": false, "type": "wrist", "rebound": false, "rush": false}, {"x": 77.0, "y": -4.0, "xg": 0.0508, "goal": true, "type": "tip-in", "rebound": false, "rush": false}, {"x": 83.0, "y": 1.0, "xg": 0.0944, "goal": false, "type": "tip-in", "rebound": false, "rush": false}, {"x": 67.0, "y": 24.0, "xg": 0.0418, "goal": false, "type": "slap", "rebound": false, "rush": false}, {"x": 30.0, "y": 38.0, "xg": 0.0093, "goal": false, "type": "wrist", "rebound": false, "rush": false}, {"x": 82.0, "y": 1.0, "xg": 0.2753, "goal": false, "type": "wrist", "rebound": true, "rush": false}, {"x": 54.0, "y": -27.0, "xg": 0.0538, "goal": false, "type": "snap", "rebound": false, "rush": false}, {"x": 72.0, "y": 8.0, "xg": 0.1598, "goal": false, "type": "snap", "rebound": false, "rush": false}, {"x": 38.0, "y": -15.0, "xg": 0.0565, "goal": false, "type": "wrist", "rebound": false, "rush": true}, {"x": 64.0, "y": 7.0, "xg": 0.092, "goal": false, "type": "snap", "rebound": false, "rush": false}, {"x": 51.0, "y": 34.0, "xg": 0.0129, "goal": false, "type": "wrist", "rebound": false, "rush": false}, {"x": 81.0, "y": 3.0, "xg": 0.1742, "goal": false, "type": "snap", "rebound": false, "rush": false}, {"x": 57.0, "y": -0.0, "xg": 0.0675, "goal": false, "type": "wrist", "rebound": false, "rush": false}, {"x": 88.0, "y": -4.0, "xg": 0.0702, "goal": false, "type": "wrist", "rebound": false, "rush": false}, {"x": 18.0, "y": 28.0, "xg": 0.006, "goal": false, "type": "tip-in", "rebound": false, "rush": false}, {"x": 81.0, "y": 0.0, "xg": 0.1295, "goal": true, "type": "backhand", "rebound": true, "rush": false}, {"x": 48.0, "y": 23.0, "xg": 0.0101, "goal": false, "type": "wrist", "rebound": false, "rush": false}, {"x": 80.0, "y": 6.0, "xg": 0.1142, "goal": true, "type": "wrist", "rebound": false, "rush": false}, {"x": 81.0, "y": -5.0, "xg": 0.1422, "goal": false, "type": "wrist", "rebound": false, "rush": false}, {"x": 35.0, "y": 21.0, "xg": 0.0166, "goal": false, "type": "wrist", "rebound": false, "rush": false}, {"x": 84.0, "y": -4.0, "xg": 0.2074, "goal": false, "type": "wrist", "rebound": true, "rush": false}, {"x": 77.0, "y": 5.0, "xg": 0.1804, "goal": false, "type": "snap", "rebound": false, "rush": false}, {"x": 83.0, "y": 2.0, "xg": 0.2987, "goal": false, "type": "snap", "rebound": true, "rush": false}, {"x": 33.0, "y": 4.0, "xg": 0.0473, "goal": false, "type": "wrist", "rebound": false, "rush": true}, {"x": 71.0, "y": -10.0, "xg": 0.0572, "goal": false, "type": "backhand", "rebound": false, "rush": false}, {"x": 84.0, "y": -11.0, "xg": 0.0824, "goal": false, "type": "backhand", "rebound": true, "rush": false}, {"x": 38.0, "y": 29.0, "xg": 0.0252, "goal": false, "type": "wrist", "rebound": false, "rush": false}, {"x": 68.0, "y": -29.0, "xg": 0.0257, "goal": false, "type": "wrist", "rebound": false, "rush": false}, {"x": 57.0, "y": 17.0, "xg": 0.0328, "goal": false, "type": "wrist", "rebound": false, "rush": false}, {"x": 83.0, "y": -5.0, "xg": 0.103, "goal": true, "type": "tip-in", "rebound": false, "rush": true}, {"x": 30.0, "y": 24.0, "xg": 0.0207, "goal": false, "type": "wrist", "rebound": false, "rush": false}, {"x": 74.0, "y": -1.0, "xg": 0.0852, "goal": false, "type": "tip-in", "rebound": false, "rush": false}, {"x": 13.0, "y": 25.0, "xg": 0.0156, "goal": false, "type": "snap", "rebound": false, "rush": false}, {"x": 65.0, "y": -15.0, "xg": 0.0556, "goal": false, "type": "wrist", "rebound": false, "rush": false}, {"x": 75.0, "y": -4.0, "xg": 0.0608, "goal": false, "type": "tip-in", "rebound": false, "rush": false}, {"x": 72.0, "y": -1.0, "xg": 0.1877, "goal": false, "type": "snap", "rebound": false, "rush": false}, {"x": 78.0, "y": -28.0, "xg": 0.0253, "goal": false, "type": "wrist", "rebound": false, "rush": false}, {"x": 85.0, "y": -9.0, "xg": 0.0243, "goal": false, "type": "wrap-around", "rebound": false, "rush": false}, {"x": 75.0, "y": 4.0, "xg": 0.0716, "goal": false, "type": "tip-in", "rebound": false, "rush": false}, {"x": 61.0, "y": -25.0, "xg": 0.0157, "goal": false, "type": "backhand", "rebound": false, "rush": false}, {"x": 78.0, "y": 1.0, "xg": 0.1073, "goal": false, "type": "wrist", "rebound": false, "rush": false}, {"x": 89.0, "y": -4.0, "xg": 0.0434, "goal": false, "type": "backhand", "rebound": true, "rush": false}, {"x": 76.0, "y": 1.0, "xg": 0.2189, "goal": false, "type": "wrist", "rebound": true, "rush": false}, {"x": 38.0, "y": -4.0, "xg": 0.0305, "goal": false, "type": "wrist", "rebound": false, "rush": false}, {"x": 52.0, "y": -16.0, "xg": 0.0685, "goal": false, "type": "wrist", "rebound": false, "rush": false}, {"x": 20.0, "y": -1.0, "xg": 0.0112, "goal": false, "type": "wrist", "rebound": false, "rush": false}, {"x": 77.0, "y": -0.0, "xg": 0.1453, "goal": true, "type": "deflected", "rebound": false, "rush": false}, {"x": 66.0, "y": -13.0, "xg": 0.0582, "goal": false, "type": "snap", "rebound": false, "rush": false}, {"x": 90.0, "y": 7.0, "xg": 0.0074, "goal": false, "type": "wrist", "rebound": false, "rush": false}, {"x": 66.0, "y": -15.0, "xg": 0.0791, "goal": false, "type": "wrist", "rebound": false, "rush": true}, {"x": 54.0, "y": 24.0, "xg": 0.0422, "goal": false, "type": "snap", "rebound": false, "rush": false}, {"x": 63.0, "y": -30.0, "xg": 0.0248, "goal": false, "type": "wrist", "rebound": false, "rush": false}, {"x": 65.0, "y": -3.0, "xg": 0.0674, "goal": false, "type": "wrist", "rebound": false, "rush": false}, {"x": 81.0, "y": -4.0, "xg": 0.0836, "goal": false, "type": "tip-in", "rebound": false, "rush": false}, {"x": 82.0, "y": 3.0, "xg": 0.0995, "goal": false, "type": "deflected", "rebound": false, "rush": false}, {"x": 72.0, "y": 11.0, "xg": 0.0801, "goal": false, "type": "wrist", "rebound": false, "rush": false}, {"x": 80.0, "y": -2.0, "xg": 0.0768, "goal": false, "type": "backhand", "rebound": false, "rush": false}, {"x": 66.0, "y": 1.0, "xg": 0.1111, "goal": false, "type": "snap", "rebound": false, "rush": true}, {"x": 79.0, "y": 4.0, "xg": 0.0966, "goal": false, "type": "backhand", "rebound": false, "rush": false}, {"x": 74.0, "y": -4.0, "xg": 0.06, "goal": false, "type": "backhand", "rebound": false, "rush": false}, {"x": 75.0, "y": 23.0, "xg": 0.1055, "goal": false, "type": "snap", "rebound": false, "rush": false}, {"x": 55.0, "y": 16.0, "xg": 0.0992, "goal": false, "type": "snap", "rebound": false, "rush": false}, {"x": 78.0, "y": 5.0, "xg": 0.0711, "goal": false, "type": "wrist", "rebound": false, "rush": false}, {"x": 67.0, "y": 11.0, "xg": 0.2183, "goal": false, "type": "snap", "rebound": true, "rush": false}, {"x": 58.0, "y": 14.0, "xg": 0.045, "goal": false, "type": "wrist", "rebound": false, "rush": false}, {"x": 56.0, "y": 23.0, "xg": 0.0299, "goal": false, "type": "wrist", "rebound": false, "rush": false}, {"x": 36.0, "y": 17.0, "xg": 0.0237, "goal": false, "type": "wrist", "rebound": false, "rush": false}], "20252026": [{"x": 60.0, "y": 17.0, "xg": 0.0884, "goal": false, "type": "wrist", "rebound": false, "rush": false}, {"x": 77.0, "y": -10.0, "xg": 0.0785, "goal": false, "type": "wrist", "rebound": false, "rush": false}, {"x": 82.0, "y": 2.0, "xg": 0.2775, "goal": false, "type": "wrist", "rebound": true, "rush": false}, {"x": 57.0, "y": 22.0, "xg": 0.0438, "goal": false, "type": "wrist", "rebound": false, "rush": false}, {"x": 34.0, "y": -0.0, "xg": 0.0182, "goal": false, "type": "wrist", "rebound": false, "rush": false}, {"x": 63.0, "y": -7.0, "xg": 0.0943, "goal": false, "type": "wrist", "rebound": false, "rush": false}, {"x": 16.0, "y": 27.0, "xg": 0.0071, "goal": false, "type": "tip-in", "rebound": false, "rush": false}, {"x": 80.0, "y": 3.0, "xg": 0.0605, "goal": false, "type": "tip-in", "rebound": false, "rush": false}, {"x": 83.0, "y": -3.0, "xg": 0.3077, "goal": false, "type": "snap", "rebound": true, "rush": false}, {"x": 80.0, "y": 4.0, "xg": 0.2364, "goal": false, "type": "wrist", "rebound": true, "rush": false}, {"x": 74.0, "y": -13.0, "xg": 0.0643, "goal": false, "type": "backhand", "rebound": false, "rush": false}, {"x": 70.0, "y": -2.0, "xg": 0.1181, "goal": false, "type": "wrist", "rebound": false, "rush": false}, {"x": 78.0, "y": 5.0, "xg": 0.2155, "goal": false, "type": "wrist", "rebound": true, "rush": false}, {"x": 83.0, "y": 5.0, "xg": 0.1055, "goal": false, "type": "tip-in", "rebound": false, "rush": true}, {"x": 86.0, "y": -8.0, "xg": 0.0633, "goal": false, "type": "deflected", "rebound": true, "rush": false}, {"x": 92.0, "y": -6.0, "xg": 0.0086, "goal": false, "type": "wrap-around", "rebound": false, "rush": false}, {"x": 76.0, "y": 0.0, "xg": 0.2257, "goal": false, "type": "snap", "rebound": false, "rush": false}, {"x": 53.0, "y": -23.0, "xg": 0.0626, "goal": false, "type": "snap", "rebound": false, "rush": true}, {"x": 75.0, "y": -9.0, "xg": 0.0425, "goal": false, "type": "backhand", "rebound": false, "rush": false}, {"x": 64.0, "y": 0.0, "xg": 0.0979, "goal": false, "type": "snap", "rebound": false, "rush": false}, {"x": 76.0, "y": 20.0, "xg": 0.042, "goal": false, "type": "wrist", "rebound": false, "rush": false}, {"x": 74.0, "y": -2.0, "xg": 0.075, "goal": false, "type": "tip-in", "rebound": false, "rush": false}]}